gladius/__init__.py
gladius/aiohttp.py
gladius/defs.py
gladius/element.py
gladius/gladius.py
gladius/imports.py
gladius/mock_module.py
gladius/script.py
gladius/starter.py
gladius/static/favicon.png
gladius/types.py
gladius/util.py
gladius-0.3.5.dist-info/LICENSE
gladius-0.3.5.dist-info/METADATA
gladius-0.3.5.dist-info/WHEEL
gladius-0.3.5.dist-info/RECORD
