Metadata-Version: 2.3
Name: gladius
Version: 0.3.5
Summary: Gladius is a library facilitating web application development exclusively in pure Python
License: MIT
Author: Tangled Group, Inc
Author-email: info@tangledgroup.com
Requires-Python: >=3.10,<4.0
Classifier: License :: OSI Approved :: MIT License
Classifier: Programming Language :: Python :: 3
Classifier: Programming Language :: Python :: 3.10
Classifier: Programming Language :: Python :: 3.11
Classifier: Programming Language :: Python :: 3.12
Classifier: Programming Language :: Python :: 3.13
Provides-Extra: all
Requires-Dist: aiohttp[speedups] (>=3.11.12,<4.0.0) ; extra == "all"
Requires-Dist: attrs (>=25.1.0,<26.0.0)
Requires-Dist: cattrs (>=24.1.2,<25.0.0)
Requires-Dist: gunicorn (==23.0.0) ; extra == "all"
Requires-Dist: nodejs-wheel (>=22.14.0,<23.0.0) ; extra == "all"
Requires-Dist: tqdm (>=4.67.1,<5.0.0)
Requires-Dist: uvloop (>=0.21.0,<0.22.0) ; extra == "all"
Project-URL: Bug Tracker, https://github.com/tangledgroup/gladius/issues
Project-URL: Documentation, https://github.com/tangledgroup/gladius
Project-URL: Homepage, https://github.com/tangledgroup/gladius
Project-URL: Repository, https://github.com/tangledgroup/gladius
